control.py
utils.py
alphaserve-0.1.2.data/scripts/alphaserve
alphaserve-0.1.2.dist-info/LICENSE
alphaserve-0.1.2.dist-info/METADATA
alphaserve-0.1.2.dist-info/WHEEL
alphaserve-0.1.2.dist-info/top_level.txt
alphaserve-0.1.2.dist-info/RECORD
